{"nodes": [{"id": "src_components_tasks_task_card_tsx", "label": "task-card.tsx", "file_type": "code", "source_file": "src\\components\\tasks\\task-card.tsx", "source_location": "L1"}, {"id": "task_card_handlesavenumber", "label": "handleSaveNumber()", "file_type": "code", "source_file": "src\\components\\tasks\\task-card.tsx", "source_location": "L27"}, {"id": "task_card_handlekeydown", "label": "handleKeyDown()", "file_type": "code", "source_file": "src\\components\\tasks\\task-card.tsx", "source_location": "L38"}, {"id": "task_card_string", "label": "String()", "file_type": "code", "source_file": "src\\components\\tasks\\task-card.tsx", "source_location": "L151"}], "edges": [{"source": "src_components_tasks_task_card_tsx", "target": "react", "relation": "imports_from", "confidence": "EXTRACTED", "source_file": "src\\components\\tasks\\task-card.tsx", "source_location": "L1", "weight": 1.0}, {"source": "src_components_tasks_task_card_tsx", "target": "lucide_react", "relation": "imports_from", "confidence": "EXTRACTED", "source_file": "src\\components\\tasks\\task-card.tsx", "source_location": "L2", "weight": 1.0}, {"source": "src_components_tasks_task_card_tsx", "target": "src_components_tasks_types", "relation": "imports_from", "confidence": "EXTRACTED", "source_file": "src\\components\\tasks\\task-card.tsx", "source_location": "L3", "weight": 1.0}, {"source": "src_components_tasks_task_card_tsx", "target": "src_components_tasks_ui_badge", "relation": "imports_from", "confidence": "EXTRACTED", "source_file": "src\\components\\tasks\\task-card.tsx", "source_location": "L4", "weight": 1.0}, {"source": "src_components_tasks_task_card_tsx", "target": "task_card_handlesavenumber", "relation": "contains", "confidence": "EXTRACTED", "source_file": "src\\components\\tasks\\task-card.tsx", "source_location": "L27", "weight": 1.0}, {"source": "src_components_tasks_task_card_tsx", "target": "task_card_handlekeydown", "relation": "contains", "confidence": "EXTRACTED", "source_file": "src\\components\\tasks\\task-card.tsx", "source_location": "L38", "weight": 1.0}, {"source": "src_components_tasks_task_card_tsx", "target": "task_card_string", "relation": "contains", "confidence": "EXTRACTED", "source_file": "src\\components\\tasks\\task-card.tsx", "source_location": "L151", "weight": 1.0}, {"source": "task_card_handlekeydown", "target": "task_card_handlesavenumber", "relation": "calls", "confidence": "EXTRACTED", "source_file": "src\\components\\tasks\\task-card.tsx", "source_location": "L39", "weight": 1.0}]}